rclonepy/__init__.py
rclonepy/rclone_actor.py
rclonepy-0.2.19.dist-info/LICENSE
rclonepy-0.2.19.dist-info/METADATA
rclonepy-0.2.19.dist-info/WHEEL
rclonepy-0.2.19.dist-info/top_level.txt
rclonepy-0.2.19.dist-info/RECORD
